django_admin_buttons/admin_button.py
django_admin_buttons/boot_django.py
django_admin_buttons/static/django_admin_buttons/django_admin_buttons.js
django_admin_buttons/templates/admin/change_list.html
django_admin_buttons-0.2.7.dist-info/METADATA
django_admin_buttons-0.2.7.dist-info/WHEEL
django_admin_buttons-0.2.7.dist-info/top_level.txt
django_admin_buttons-0.2.7.dist-info/RECORD
