Metadata-Version: 2.1
Name: django_admin_buttons
Version: 0.2.7
Summary: Django admin button
Home-page: https://github.com/minaaaatef/Django-Admin-Buttons
Author: Mina Atef
Author-email: mina.atef0@gmail.com
License: MIT
Keywords: django,buttons,admin,actions
Classifier: Development Status :: 5 - Production/Stable
Classifier: Environment :: Web Environment
Classifier: Intended Audience :: Developers
Classifier: License :: OSI Approved :: MIT License
Classifier: Operating System :: OS Independent
Classifier: Programming Language :: Python :: 3 :: Only
Classifier: Programming Language :: Python :: 3.7
Classifier: Programming Language :: Python :: Implementation :: CPython
Classifier: Topic :: Software Development :: Libraries :: Application Frameworks
Classifier: Topic :: Software Development :: Libraries :: Python Modules
Classifier: Framework :: Django
Requires-Python: >=3.6
Requires-Dist: Django>=2.2
